qbasic/__init__.py
qbasic/class_tijolo.py
qbasic/estados.py
qbasic/funçoes.py
qbasic/operador.py
Q_BASIC-0.0.3.dist-info/METADATA
Q_BASIC-0.0.3.dist-info/WHEEL
Q_BASIC-0.0.3.dist-info/top_level.txt
Q_BASIC-0.0.3.dist-info/RECORD
