Metadata-Version: 2.1
Name: Q-BASIC
Version: 0.0.3
Summary: Q-BASIC (Quantum Brazilian Algorithms, Simulations, and Computational tools)
Home-page: https://github.com/GubioGL/Q-Basic
Author: Gubio Gomes de lima
Author-email: gubiofisikal@gmail.com
Classifier: Programming Language :: Python :: 3
Classifier: License :: OSI Approved :: MIT License
Classifier: Operating System :: OS Independent
Requires-Python: >=3.10.16
Requires-Dist: tqdm==4.67.1
Requires-Dist: sympy==1.13.1
Requires-Dist: torch==2.5.1+cu118
Requires-Dist: scipy==1.14.1
